AUTHORS
ChangeLog
LICENSE
Pipfile
Pipfile.lock
README.md
main.py
setup.cfg
setup.py
.github/workflows/build.yml
.github/workflows/publish.yml
docs/screenshot_01.png
docs/screenshot_02.png
docs/screenshot_03.png
docs/screenshot_04.png
jfmp/__init__.py
jfmp/app.py
jfmp/client.py
jfmp/constants.py
jfmp/data.py
jfmp/file.py
jfmp/gui.py
jfmp/interfaces.py
jfmp/player.py
jfmp.egg-info/PKG-INFO
jfmp.egg-info/SOURCES.txt
jfmp.egg-info/dependency_links.txt
jfmp.egg-info/entry_points.txt
jfmp.egg-info/not-zip-safe
jfmp.egg-info/pbr.json
jfmp.egg-info/top_level.txt