Metadata-Version: 2.1
Name: jfmp
Version: 0.0.1
Summary: A minimalist cross-platform gapless music player for Jellyfin
Home-page: https://github.com/n-peugnet/jfmp
Author: Nicolas Peugnet
Author-email: n.peugnet@free.fr
License: UNKNOWN
Platform: UNKNOWN
Classifier: Programming Language :: Python :: 3
Classifier: License :: OSI Approved :: GNU General Public License v3 (GPLv3)
Classifier: Operating System :: OS Independent
Requires-Python: >=3.6
